{
  "header": "Sustainable Development Solutions Network - Antarctica",
  "subtitle": "<p>Translating the latest expertise in sustainable development into action in Antarctica</p>",
  "featureTitle": "About the network",
  "featureContent": "<p>The Sustainable Development Solutions Network (SDSN) a global community of universities, research centers, and knowledge institutions. Our National network aims to teach sustainable development, support solution initiatives, and localize the SDGs in Antarctica.</p><p>We engage with scientists, engineers, business and civil society leaders, and development practitioners for evidence-based problem-solving. </p>",
  "map": "<iframe src=\"https://www.google.com/maps/embed?pb=!1m18!1m12!1m3!1d4085558.0419548173!2d35.66468386426656!3d0.15993979223273572!2m3!1f0!2f0!3f0!3m2!1i1024!2i768!4f13.1!3m3!1m2!1s0x182780d08350900f%3A0x403b0eb0a1976dd9!2sKenya!5e0!3m2!1sen!2sau!4v1596773220404!5m2!1sen!2sau\" width=\"600\" height=\"450\" frameborder=\"0\" style=\"border:0;\" allowfullscreen=\"\" aria-hidden=\"false\" tabindex=\"0\"></iframe>",
  "newsHeader": "Recent News",
  "newsSubtitle": "Read more about our current work",
  "homeCtaTitle": "Contact us",
  "homeCtaText": "Get in touch at antarc@unsdsn.org",
  "title": "Page: Homepage",
  "showBenefits": true,
  "involvedBenefits": [
    {
      "desc": "",
      "header": "Get access to academic expertise and work together with different sectors"
    },
    {
      "header": "Contribute to the sustainable development in your community",
      "desc": ""
    },
    {
      "desc": "",
      "header": "Get access to tools, resources, and opportunities to further your solutions"
    }
  ],
  "benefitsTitle": "Join our global network and work on practical solutions for sustainable development"
}
